_temporal_random_walk.cpython-310-x86_64-linux-gnu.so
temporal_random_walk/__init__.py
temporal_random_walk.libs/libcuda-43c1b388.so.570.124.06
temporal_random_walk.libs/libcudart-09529672.so.12.6.77
temporal_random_walk.libs/libcurand-12411c1e.so.10.3.7.77
temporal_random_walk.libs/libgomp-0e7565f6.so.1.0.0
temporal_random_walk.libs/libtbb-163ea319.so.2
temporal_random_walk-1.4.3.dist-info/METADATA
temporal_random_walk-1.4.3.dist-info/WHEEL
temporal_random_walk-1.4.3.dist-info/top_level.txt
temporal_random_walk-1.4.3.dist-info/RECORD
