Metadata-Version: 2.4
Name: temporal_random_walk
Version: 1.4.3
Summary: A library to sample temporal random walks from in-memory temporal graphs
Home-page: https://github.com/ashfaq1701/temporal-random-walk
Author: Ashfaq Salehin
Author-email: ashfaq.salehin1701@gmail.com
Requires-Python: >=3.8
Requires-Dist: pybind11>=2.6.0
Requires-Dist: numpy
Requires-Dist: networkx
Dynamic: author
Dynamic: author-email
Dynamic: description
Dynamic: description-content-type
Dynamic: home-page
Dynamic: requires-dist
Dynamic: requires-python
Dynamic: summary
